fsd/FirstPromptAgent.py
fsd/__init__.py
fsd/io.py
fsd/main.py
fsd/repo.py
fsd/repomap.py
fsd/Crawler/CrawlerAgent.py
fsd/Crawler/CrawlerTaskPlanner.py
fsd/Deployment/DeploymentCheckAgent.py
fsd/Deployment/DeploymentControllerAgent.py
fsd/ImageAgent/ImageAnalysAgent.py
fsd/ImageAgent/ImageCheckSpecialAgent.py
fsd/ImageAgent/ImageControllerAgent.py
fsd/ImageAgent/ImageGenAgent.py
fsd/ImageAgent/ImagePrePromptAgent.py
fsd/ImageAgent/ImageTaskPlanner.py
fsd/MainOperation/MainBuilderAgent.py
fsd/MainOperation/ProjectManager.py
fsd/MainOperation/ProjectsRunner.py
fsd/MainOperation/__init__.py
fsd/PromptImageUrlAgent/PromptImageUrlAgent.py
fsd/coding_agent/BugTaskPlanner.py
fsd/coding_agent/CodingAgent.py
fsd/coding_agent/ContextBugAgent.py
fsd/coding_agent/ContextPrepareAgent.py
fsd/coding_agent/ControllerAgent.py
fsd/coding_agent/FileManagerAgent.py
fsd/coding_agent/IdeaDevelopment.py
fsd/coding_agent/InitNewProjectAgent.py
fsd/coding_agent/LintPlanner.py
fsd/coding_agent/PrePromptAgent.py
fsd/coding_agent/SearchAgent.py
fsd/coding_agent/TaskPlanner.py
fsd/coding_agent/__init__.py
fsd/compile/CompileFileFinderAgent.py
fsd/compile/CompileGuiderAgent.py
fsd/compile/CompilePrePromptAgent.py
fsd/compile/CompileProjectAnalysAgent.py
fsd/compile/CompileTaskPlanner.py
fsd/compile/compileControllerAgent.py
fsd/dependency/DependencyCheckAgent.py
fsd/dependency/DependencyCheckCLIAgent.py
fsd/dependency/DependencyControllerAgent.py
fsd/dependency/DependencyFileFinderAgent.py
fsd/dependency/DependencyGuiderAgent.py
fsd/dependency/DependencyPrePromptAgent.py
fsd/dependency/DependencyProjectAnalysAgent.py
fsd/dependency/DependencyTaskPlanner.py
fsd/explainer/ExplainableFileFinderAgent.py
fsd/explainer/ExplainablePrePromptAgent.py
fsd/explainer/ExplainerController.py
fsd/explainer/GeneralExplainerAgent.py
fsd/explainer/MainExplainerAgent.py
fsd/explainer/__init__.py
fsd/log/custom_format.py
fsd/log/logger_config.py
fsd/queries/README.md
fsd/queries/tree-sitter-c-tags.scm
fsd-0.1.660.dist-info/METADATA
fsd-0.1.660.dist-info/WHEEL
fsd-0.1.660.dist-info/top_level.txt
fsd-0.1.660.dist-info/RECORD
