Metadata-Version: 2.1
Name: fsd
Version: 0.1.660
Summary: Core engine powering Zinley Studio - an AI-powered development environment
Home-page: https://github.com/Zinley-dev/fsd_v2_universal
Author: Zinley
Author-email: dev@zinley.com
License: UNKNOWN
Platform: UNKNOWN
Classifier: Programming Language :: Python :: 3
Classifier: License :: OSI Approved :: MIT License
Classifier: Operating System :: OS Independent
Requires-Python: >=3.6
Requires-Dist: aiohttp==3.11.0
Requires-Dist: pbxproj==4.2.1
Requires-Dist: portkey-ai==1.9.9
Requires-Dist: pycparser==2.22
Requires-Dist: requests==2.32.3
Requires-Dist: urllib3==2.2.3
Requires-Dist: json-repair==0.30.2
Requires-Dist: setuptools==75.2.0
Requires-Dist: gitdb==4.0.11
Requires-Dist: gitpython==3.1.43
Requires-Dist: grep-ast==0.8.1
Requires-Dist: tqdm==4.66.5
Requires-Dist: tree-sitter==0.24.0
Requires-Dist: tree-sitter-c-sharp==0.23.1
Requires-Dist: tree-sitter-embedded-template==0.23.2
Requires-Dist: tree-sitter-language-pack==0.7.1
Requires-Dist: tree-sitter-yaml==0.7.0
Requires-Dist: typing-extensions==4.13.2
Requires-Dist: diskcache==5.6.3
Requires-Dist: firecrawl-py==1.3.1
Requires-Dist: pypdf2==3.0.1
Requires-Dist: python-docx==1.1.2
Requires-Dist: chardet==5.2.0
Requires-Dist: openpyxl==3.1.5
Requires-Dist: et-xmlfile==1.1.0
Requires-Dist: boto3==1.35.44
Requires-Dist: backoff==2.2.1
Requires-Dist: aiofiles==24.1.0
Requires-Dist: certifi==2024.8.30
Requires-Dist: rapidfuzz==3.10.1
Requires-Dist: psutil==6.1.0
Requires-Dist: docx==0.2.4
Requires-Dist: prompt-toolkit==3.0.48
Requires-Dist: networkx==3.4.2
Requires-Dist: numpy==2.1.3
Requires-Dist: scipy==1.14.1
Requires-Dist: tiktoken==0.8.0
Requires-Dist: flake8==7.1.1
Requires-Dist: httpx==0.27.1
Requires-Dist: rich==13.9.4
